{"mc":{"wlk_1":{"frameRate":10,"labels":null,"frames":[{"res":"10000","x":-45,"y":-114},{"res":"10001","x":-39,"y":-115},{"res":"10002","x":-37,"y":-114},{"res":"10003","x":-39,"y":-113},{"res":"10004","x":-43,"y":-114},{"res":"10005","x":-47,"y":-115},{"res":"10006","x":-48,"y":-113},{"res":"10007","x":-47,"y":-111}]}},"res":{"10000":{"x":0,"y":0,"w":96,"h":136},"10001":{"x":96,"y":0,"w":91,"h":137},"10002":{"x":187,"y":0,"w":89,"h":134},"10003":{"x":276,"y":0,"w":90,"h":136},"10004":{"x":366,"y":0,"w":92,"h":137},"10005":{"x":458,"y":0,"w":96,"h":137},"10006":{"x":554,"y":0,"w":96,"h":134},"10007":{"x":650,"y":0,"w":96,"h":134}}}
