{"mc":{"at01_5":{"frameRate":14,"labels":null,"frames":[{"res":"050000","x":-89,"y":-211},{"res":"050001","x":-73,"y":-239},{"res":"050002","x":-66,"y":-214},{"res":"050003","x":-66,"y":-202},{"res":"050004","x":-74,"y":-199},{"res":"050005","x":-60,"y":-239},{"res":"050006","x":-59,"y":-236},{"res":"050007","x":-59,"y":-240},{"res":"050008","x":-57,"y":-253},{"res":"050010","x":-68,"y":-256}]}},"res":{"050000":{"x":0,"y":0,"w":164,"h":238},"050001":{"x":164,"y":0,"w":184,"h":265},"050002":{"x":348,"y":0,"w":236,"h":240},"050003":{"x":584,"y":0,"w":133,"h":228},"050004":{"x":717,"y":0,"w":140,"h":225},"050005":{"x":857,"y":0,"w":124,"h":250},"050006":{"x":981,"y":0,"w":124,"h":246},"050007":{"x":0,"y":265,"w":122,"h":251},"050008":{"x":122,"y":265,"w":121,"h":267},"050010":{"x":243,"y":265,"w":138,"h":279}}}
