{"mc":{"at01_4":{"frameRate":10,"labels":null,"frames":[{"res":"40000","x":-98,"y":-136},{"res":"40001","x":-64,"y":-160},{"res":"40002","x":-72,"y":-159},{"res":"40003","x":-60,"y":-158},{"res":"40004","x":-61,"y":-150},{"res":"40005","x":-120,"y":-155},{"res":"40006","x":-101,"y":-137},{"res":"40007","x":-97,"y":-128},{"res":"40008","x":-106,"y":-127},{"res":"40009","x":-106,"y":-152}]}},"res":{"40000":{"x":0,"y":0,"w":178,"h":154},"40001":{"x":178,"y":0,"w":124,"h":180},"40002":{"x":302,"y":0,"w":134,"h":169},"40003":{"x":436,"y":0,"w":136,"h":193},"40004":{"x":572,"y":0,"w":141,"h":159},"40005":{"x":713,"y":0,"w":183,"h":170},"40006":{"x":896,"y":0,"w":149,"h":183},"40007":{"x":0,"y":193,"w":145,"h":165},"40008":{"x":145,"y":193,"w":154,"h":173},"40009":{"x":299,"y":193,"w":218,"h":165}}}
