{"mc":{"wlk_2":{"frameRate":9,"labels":null,"frames":[{"res":"20000","x":-77,"y":-123},{"res":"20002","x":-76,"y":-123},{"res":"20004","x":-75,"y":-124},{"res":"20006","x":-73,"y":-124},{"res":"20008","x":-73,"y":-123},{"res":"20010","x":-77,"y":-123},{"res":"20012","x":-78,"y":-124}]}},"res":{"20000":{"x":0,"y":0,"w":139,"h":140},"20002":{"x":139,"y":0,"w":137,"h":137},"20004":{"x":276,"y":0,"w":136,"h":134},"20006":{"x":412,"y":0,"w":134,"h":130},"20008":{"x":546,"y":0,"w":133,"h":130},"20010":{"x":679,"y":0,"w":137,"h":127},"20012":{"x":816,"y":0,"w":140,"h":136}}}
